{
    "4": [
        {
            "start": 4,
            "end": 9,
            "refs": {
                "Bava Batra 2a": "בבא בתרא ב׳ א"
            }
        }
    ],
    "12": [
        {
            "start": 3786,
            "end": 3802,
            "refs": {
                "Bava Metzia 110": "בבא מציעא ק״י"
            }
        },
        {
            "start": 4241,
            "end": 4245,
            "refs": {
                "Bava Metzia 110a": "בבא מציעא ק״י א"
            }
        },
        {
            "start": 4308,
            "end": 4312,
            "refs": {
                "Bava Metzia 110a": "בבא מציעא ק״י א"
            }
        }
    ],
    "49": [
        {
            "start": 1084,
            "end": 1093,
            "refs": {
                "Bava Metzia 113": "בבא מציעא קי״ג"
            }
        }
    ],
    "52": [
        {
            "start": 267,
            "end": 278,
            "refs": {
                "Bava Batra 28a:1-60b:22": "בבא בתרא כ״ח א:א׳-ס׳ ב:כ״ב",
                "Jerusalem Talmud Bava Batra 3:1:1-11:2": "תלמוד ירושלמי בבא בתרא ג׳:א׳:א׳-י״א:ב׳"
            }
        },
        {
            "start": 1041,
            "end": 1052,
            "refs": {
                "Bava Batra 28a:1-60b:22": "בבא בתרא כ״ח א:א׳-ס׳ ב:כ״ב",
                "Jerusalem Talmud Bava Batra 3:1:1-11:2": "תלמוד ירושלמי בבא בתרא ג׳:א׳:א׳-י״א:ב׳"
            }
        }
    ],
    "53": [
        {
            "start": 2773,
            "end": 2789,
            "refs": {
                "Bava Batra 61a:1-73a:2": "בבא בתרא ס״א א:א׳-ע״ג א:ב׳",
                "Jerusalem Talmud Bava Batra 4:1:1-8:4": "תלמוד ירושלמי בבא בתרא ד׳:א׳:א׳-ח׳:ד׳"
            }
        }
    ],
    "63": [
        {
            "start": 4962,
            "end": 4978,
            "refs": {
                "Bava Metzia 110": "בבא מציעא ק״י"
            }
        },
        {
            "start": 5344,
            "end": 5358,
            "refs": {
                "Mishneh Torah, Neighbors 6": "משנה תורה, הלכות שכנים ו׳"
            }
        }
    ],
    "65": [
        {
            "start": 1332,
            "end": 1349,
            "refs": {
                "Gittin 60b": "גיטין ס׳ ב"
            }
        }
    ],
    "66": [
        {
            "start": 634,
            "end": 649,
            "refs": {
                "Bava Kamma 27a:13-36a:8": "בבא קמא כ״ז א:י״ג-ל״ו א:ח׳"
            }
        },
        {
            "start": 715,
            "end": 723,
            "refs": {
                "Tosafot on Bava Kamma 27a": "תוספות על בבא קמא כ״ז א"
            }
        }
    ],
    "69": [
        {
            "start": 4,
            "end": 8,
            "refs": {
                "Bava Metzia 7": "בבא מציעא ז׳"
            }
        }
    ],
    "70": [
        {
            "start": 210,
            "end": 213,
            "refs": {
                "Mishnah Bava Metzia 8": "משנה בבא מציעא ח׳",
                "Bava Metzia 88": "בבא מציעא פ״ח",
                "Bava Metzia 94a:16-103a:15": "בבא מציעא צ״ד א:ט״ז-ק״ג א:ט״ו"
            }
        },
        {
            "start": 703,
            "end": 720,
            "refs": {
                "Shabbat 79a": "שבת ע״ט א"
            }
        },
        {
            "start": 833,
            "end": 838,
            "refs": {
                "Shabbat 79a": "שבת ע״ט א",
                "Bava Metzia 88a": "בבא מציעא פ״ח א",
                "Bava Metzia 94a": "בבא מציעא צ״ד א"
            }
        },
        {
            "start": 1234,
            "end": 1239,
            "refs": {
                "Bava Metzia 94a:16-103a:15": "בבא מציעא צ״ד א:ט״ז-ק״ג א:ט״ו"
            }
        },
        {
            "start": 2854,
            "end": 2858,
            "refs": {
                "Bava Metzia 94a": "בבא מציעא צ״ד א"
            }
        },
        {
            "start": 3088,
            "end": 3092,
            "refs": {
                "Bava Metzia 94a": "בבא מציעא צ״ד א"
            }
        }
    ],
    "76": [
        {
            "start": 281,
            "end": 296,
            "refs": {
                "Mishneh Torah, Neighbors 1": "משנה תורה, הלכות שכנים א׳"
            }
        }
    ],
    "77": [
        {
            "start": 1428,
            "end": 1439,
            "refs": {
                "Bava Batra 17a:8-27b:24": "בבא בתרא י״ז א:ח׳-כ״ז ב:כ״ד",
                "Jerusalem Talmud Bava Batra 2:1:1-11:5": "תלמוד ירושלמי בבא בתרא ב׳:א׳:א׳-י״א:ה׳"
            }
        }
    ],
    "86": [
        {
            "start": 7755,
            "end": 7772,
            "refs": {
                "Ketubot 69a": "כתובות ס״ט א"
            }
        }
    ],
    "87": [
        {
            "start": 3964,
            "end": 3973,
            "refs": {
                "Bava Kamma 55b:1-62b:6": "בבא קמא נ״ה ב:א׳-ס״ב ב:ו׳",
                "Jerusalem Talmud Bava Kamma 6:1:1-8:2": "תלמוד ירושלמי בבא קמא ו׳:א׳:א׳-ח׳:ב׳"
            }
        }
    ]
}