{
    "4": [
        {
            "start": 4,
            "end": 15,
            "refs": {
                "Genesis 1:1-6:8": "בראשית א׳:א׳-ו׳:ח׳"
            }
        }
    ],
    "6": [
        {
            "start": 4,
            "end": 11,
            "refs": {
                "Genesis 6:9-11:32": "בראשית ו׳:ט׳-י״א:ל״ב"
            }
        }
    ],
    "9": [
        {
            "start": 4,
            "end": 13,
            "refs": {
                "Genesis 18:1-22:24": "בראשית י״ח:א׳-כ״ב:כ״ד"
            }
        }
    ],
    "11": [
        {
            "start": 4,
            "end": 15,
            "refs": {
                "Genesis 25:19-28:9": "בראשית כ״ה:י״ט-כ״ח:ט׳"
            }
        }
    ],
    "21": [
        {
            "start": 4,
            "end": 13,
            "refs": {
                "Genesis 28:10-32:3": "בראשית כ״ח:י׳-ל״ב:ג׳"
            }
        }
    ],
    "34": [
        {
            "start": 4,
            "end": 14,
            "refs": {
                "Genesis 32:4-36:43": "בראשית ל״ב:ד׳-ל״ו:מ״ג"
            }
        }
    ],
    "38": [
        {
            "start": 4,
            "end": 13,
            "refs": {
                "Genesis 37:1-40:23": "בראשית ל״ז:א׳-מ׳:כ״ג"
            }
        }
    ],
    "46": [
        {
            "start": 4,
            "end": 12,
            "refs": {
                "Genesis 41:1-44:17": "בראשית מ״א:א׳-מ״ד:י״ז"
            }
        }
    ],
    "63": [
        {
            "start": 4,
            "end": 13,
            "refs": {
                "Genesis 44:18-47:27": "בראשית מ״ד:י״ח-מ״ז:כ״ז"
            }
        }
    ],
    "77": [
        {
            "start": 4,
            "end": 13,
            "refs": {
                "Genesis 47:28-50:26": "בראשית מ״ז:כ״ח-נ׳:כ״ו"
            }
        }
    ],
    "109": [
        {
            "start": 4,
            "end": 13,
            "refs": {
                "Exodus 1:1-6:1": "שמות א׳:א׳-ו׳:א׳"
            }
        }
    ],
    "113": [
        {
            "start": 2045,
            "end": 2060,
            "refs": {
                "Pirkei Avot 2": "משנה אבות ב׳"
            }
        }
    ],
    "128": [
        {
            "start": 4,
            "end": 13,
            "refs": {
                "Exodus 6:2-9:35": "שמות ו׳:ב׳-ט׳:ל״ה"
            }
        }
    ],
    "133": [
        {
            "start": 4,
            "end": 11,
            "refs": {
                "Exodus 10:1-13:16": "שמות י׳:א׳-י״ג:ט״ז"
            }
        }
    ],
    "143": [
        {
            "start": 4,
            "end": 13,
            "refs": {
                "Exodus 13:17-17:16": "שמות י״ג:י״ז-י״ז:ט״ז",
                "Numbers 13:1-15:41": "במדבר י״ג:א׳-ט״ו:מ״א"
            }
        }
    ],
    "151": [
        {
            "start": 119,
            "end": 128,
            "refs": {
                "Jeremiah 31": "ירמיהו ל״א"
            }
        }
    ],
    "159": [
        {
            "start": 4,
            "end": 13,
            "refs": {
                "Exodus 18:1-20:23": "שמות י״ח:א׳-כ׳:כ״ג"
            }
        }
    ],
    "167": [
        {
            "start": 4,
            "end": 15,
            "refs": {
                "Exodus 21:1-24:18": "שמות כ״א:א׳-כ״ד:י״ח"
            }
        }
    ],
    "188": [
        {
            "start": 4,
            "end": 14,
            "refs": {
                "Exodus 25:1-27:19": "שמות כ״ה:א׳-כ״ז:י״ט"
            }
        }
    ],
    "189": [
        {
            "start": 2959,
            "end": 2964,
            "refs": {
                "Exodus 25:1": "שמות כ״ה:א׳"
            }
        },
        {
            "start": 3055,
            "end": 3060,
            "refs": {
                "Exodus 25:1": "שמות כ״ה:א׳"
            }
        }
    ],
    "193": [
        {
            "start": 42,
            "end": 51,
            "refs": {
                "Pirkei Avot 1": "משנה אבות א׳"
            }
        }
    ],
    "218": [
        {
            "start": 4,
            "end": 15,
            "refs": {
                "Exodus 30:11-34:35": "שמות ל׳:י״א-ל״ד:ל״ה"
            }
        }
    ],
    "235": [
        {
            "start": 4,
            "end": 14,
            "refs": {
                "Exodus 35:1-38:20": "שמות ל״ה:א׳-ל״ח:כ׳"
            }
        }
    ],
    "237": [
        {
            "start": 147,
            "end": 156,
            "refs": {
                "Pirkei Avot 4": "משנה אבות ד׳"
            }
        }
    ],
    "243": [
        {
            "start": 4,
            "end": 14,
            "refs": {
                "Exodus 38:21-40:38": "שמות ל״ח:כ״א-מ׳:ל״ח"
            }
        }
    ],
    "265": [
        {
            "start": 4,
            "end": 14,
            "refs": {
                "Leviticus 1:1-5:26": "ויקרא א׳:א׳-ה׳:כ״ו"
            }
        }
    ],
    "270": [
        {
            "start": 4,
            "end": 11,
            "refs": {
                "Leviticus 6:1-8:36": "ויקרא ו׳:א׳-ח׳:ל״ו"
            }
        }
    ],
    "300": [
        {
            "start": 4,
            "end": 14,
            "refs": {
                "Leviticus 9:1-11:47": "ויקרא ט׳:א׳-י״א:מ״ז"
            }
        }
    ],
    "313": [
        {
            "start": 4,
            "end": 14,
            "refs": {
                "Leviticus 12:1-13:59": "ויקרא י״ב:א׳-י״ג:נ״ט"
            }
        }
    ],
    "320": [
        {
            "start": 696,
            "end": 708,
            "refs": {
                "Leviticus 19:1-20:27": "ויקרא י״ט:א׳-כ׳:כ״ז"
            }
        }
    ],
    "321": [
        {
            "start": 4,
            "end": 14,
            "refs": {
                "Leviticus 14:1-15:33": "ויקרא י״ד:א׳-ט״ו:ל״ג"
            }
        }
    ],
    "322": [
        {
            "start": 77,
            "end": 83,
            "refs": {
                "Leviticus 14:1-15:33": "ויקרא י״ד:א׳-ט״ו:ל״ג"
            }
        }
    ],
    "333": [
        {
            "start": 4,
            "end": 15,
            "refs": {
                "Leviticus 19:1-20:27": "ויקרא י״ט:א׳-כ׳:כ״ז"
            }
        }
    ],
    "347": [
        {
            "start": 4,
            "end": 13,
            "refs": {
                "Leviticus 21:1-24:23": "ויקרא כ״א:א׳-כ״ד:כ״ג"
            }
        }
    ],
    "359": [
        {
            "start": 4,
            "end": 12,
            "refs": {
                "Leviticus 25:1-26:2": "ויקרא כ״ה:א׳-כ״ו:ב׳"
            }
        }
    ],
    "384": [
        {
            "start": 4,
            "end": 14,
            "refs": {
                "Numbers 1:1-4:20": "במדבר א׳:א׳-ד׳:כ׳"
            }
        }
    ],
    "404": [
        {
            "start": 4,
            "end": 12,
            "refs": {
                "Numbers 4:21-7:89": "במדבר ד׳:כ״א-ז׳:פ״ט"
            }
        }
    ],
    "405": [
        {
            "start": 201,
            "end": 206,
            "refs": {
                "Numbers 4:21": "במדבר ד׳:כ״א"
            }
        }
    ],
    "409": [
        {
            "start": 48,
            "end": 52,
            "refs": {
                "Numbers 4:21": "במדבר ד׳:כ״א"
            }
        }
    ],
    "414": [
        {
            "start": 4,
            "end": 16,
            "refs": {
                "Numbers 8:1-12:16": "במדבר ח׳:א׳-י״ב:ט״ז"
            }
        }
    ],
    "431": [
        {
            "start": 4,
            "end": 15,
            "refs": {
                "Numbers 13:1-15:41": "במדבר י״ג:א׳-ט״ו:מ״א"
            }
        }
    ],
    "440": [
        {
            "start": 4,
            "end": 12,
            "refs": {
                "Numbers 16:1-18:32": "במדבר ט״ז:א׳-י״ח:ל״ב"
            }
        }
    ],
    "450": [
        {
            "start": 4,
            "end": 12,
            "refs": {
                "Numbers 19:1-22:1": "במדבר י״ט:א׳-כ״ב:א׳"
            }
        }
    ],
    "454": [
        {
            "start": 4,
            "end": 12,
            "refs": {
                "Numbers 22:2-25:9": "במדבר כ״ב:ב׳-כ״ה:ט׳"
            }
        }
    ],
    "469": [
        {
            "start": 4,
            "end": 13,
            "refs": {
                "Numbers 30:2-32:42": "במדבר ל׳:ב׳-ל״ב:מ״ב"
            }
        }
    ],
    "473": [
        {
            "start": 4,
            "end": 13,
            "refs": {
                "Numbers 33:1-36:13": "במדבר ל״ג:א׳-ל״ו:י״ג"
            }
        }
    ],
    "474": [
        {
            "start": 1099,
            "end": 1105,
            "refs": {
                "Numbers 33:1": "במדבר ל״ג:א׳"
            }
        }
    ],
    "478": [
        {
            "start": 4,
            "end": 14,
            "refs": {
                "Deuteronomy 1:1-3:22": "דברים א׳:א׳-ג׳:כ״ב"
            }
        }
    ],
    "489": [
        {
            "start": 4,
            "end": 15,
            "refs": {
                "Deuteronomy 3:23-7:11": "דברים ג׳:כ״ג-ז׳:י״א"
            }
        }
    ],
    "514": [
        {
            "start": 4,
            "end": 12,
            "refs": {
                "Deuteronomy 7:12-11:25": "דברים ז׳:י״ב-י״א:כ״ה"
            }
        }
    ],
    "520": [
        {
            "start": 4,
            "end": 12,
            "refs": {
                "Deuteronomy 11:26-16:17": "דברים י״א:כ״ו-ט״ז:י״ז"
            }
        }
    ],
    "528": [
        {
            "start": 4,
            "end": 15,
            "refs": {
                "Deuteronomy 16:18-21:9": "דברים ט״ז:י״ח-כ״א:ט׳"
            }
        }
    ],
    "565": [
        {
            "start": 4,
            "end": 14,
            "refs": {
                "Deuteronomy 29:9-30:20": "דברים כ״ט:ט׳-ל׳:כ׳"
            }
        }
    ],
    "574": [
        {
            "start": 4,
            "end": 13,
            "refs": {
                "Deuteronomy 31:1-30": "דברים ל״א:א׳-ל׳"
            }
        }
    ],
    "575": [
        {
            "start": 18,
            "end": 23,
            "refs": {
                "Deuteronomy 31:1": "דברים ל״א:א׳"
            }
        }
    ],
    "578": [
        {
            "start": 4,
            "end": 15,
            "refs": {
                "Deuteronomy 32:1-52": "דברים ל״ב:א׳-נ״ב"
            }
        }
    ],
    "604": [
        {
            "start": 12,
            "end": 40,
            "refs": {
                "Zohar, Tetzaveh 14:127-16:138": "ספר הזהר, תצוה י״ד:קכ״ז-ט״ז:קל״ח"
            }
        }
    ],
    "606": [
        {
            "start": 14,
            "end": 23,
            "refs": {
                "Psalms 148": "תהילים קמ״ח"
            }
        },
        {
            "start": 214,
            "end": 222,
            "refs": {
                "Psalms 148": "תהילים קמ״ח",
                "Zohar": "ספר הזהר"
            }
        }
    ],
    "609": [
        {
            "start": 14,
            "end": 25,
            "refs": {
                "Proverbs 3:29": "משלי ג׳:כ״ט"
            }
        }
    ],
    "621": [
        {
            "start": 3,
            "end": 16,
            "refs": {
                "Pirkei Avot 3": "משנה אבות ג׳"
            }
        }
    ],
    "623": [
        {
            "start": 3,
            "end": 26,
            "refs": {
                "Megillah 29a": "מגילה כ״ט א"
            }
        }
    ],
    "635": [
        {
            "start": 4,
            "end": 12,
            "refs": {
                "Genesis 41:1-44:17": "בראשית מ״א:א׳-מ״ד:י״ז"
            }
        }
    ],
    "637": [
        {
            "start": 4,
            "end": 13,
            "refs": {
                "Genesis 44:18-47:27": "בראשית מ״ד:י״ח-מ״ז:כ״ז"
            }
        }
    ],
    "638": [
        {
            "start": 33,
            "end": 35,
            "refs": {
                "Genesis 44:52": "בראשית מ״ד:נ״ב"
            }
        }
    ],
    "640": [
        {
            "start": 4,
            "end": 13,
            "refs": {
                "Exodus 1:1-6:1": "שמות א׳:א׳-ו׳:א׳"
            }
        }
    ]
}