{
    "14": [
        {
            "start": 197,
            "end": 199,
            "refs": {
                "Genesis 6:9-11:32": "בראשית ו׳:ט׳-י״א:ל״ב"
            }
        },
        {
            "start": 230,
            "end": 232,
            "refs": {
                "Genesis 6:59": "בראשית ו׳:נ״ט"
            }
        },
        {
            "start": 233,
            "end": 235,
            "refs": {
                "Genesis 6:69": "בראשית ו׳:ס״ט"
            }
        },
        {
            "start": 262,
            "end": 263,
            "refs": {
                "Genesis 6:70": "בראשית ו׳:ע׳"
            }
        },
        {
            "start": 264,
            "end": 266,
            "refs": {
                "Genesis 6:73": "בראשית ו׳:ע״ג"
            }
        },
        {
            "start": 290,
            "end": 292,
            "refs": {
                "Genesis 6:74": "בראשית ו׳:ע״ד"
            }
        },
        {
            "start": 293,
            "end": 295,
            "refs": {
                "Genesis 6:89": "בראשית ו׳:פ״ט"
            }
        },
        {
            "start": 318,
            "end": 319,
            "refs": {
                "Genesis 6:90": "בראשית ו׳:צ׳"
            }
        },
        {
            "start": 320,
            "end": 322,
            "refs": {
                "Genesis 6:110": "בראשית ו׳:ק״י"
            }
        },
        {
            "start": 346,
            "end": 349,
            "refs": {
                "Genesis 6:111": "בראשית ו׳:קי״א"
            }
        },
        {
            "start": 350,
            "end": 353,
            "refs": {
                "Genesis 6:114": "בראשית ו׳:קי״ד"
            }
        },
        {
            "start": 377,
            "end": 380,
            "refs": {
                "Genesis 6:115": "בראשית ו׳:קט״ו"
            }
        },
        {
            "start": 381,
            "end": 382,
            "refs": {
                "Genesis 30": "בראשית ל׳"
            }
        }
    ],
    "134": [
        {
            "start": 423,
            "end": 432,
            "refs": {
                "Proverbs 16:4": "משלי ט״ז:ד׳"
            }
        }
    ],
    "303": [
        {
            "start": 41,
            "end": 43,
            "refs": {
                "Leviticus 6:1-8:36": "ויקרא ו׳:א׳-ח׳:ל״ו"
            }
        }
    ],
    "428": [
        {
            "start": 225,
            "end": 237,
            "refs": {
                "Genesis 2:24": "בראשית ב׳:כ״ד"
            }
        }
    ]
}